Workbook

Sheet 每日記錄 Daily Input
A1: 每日財務記錄 Daily Financial Input
A2: 日期 Date | B2: 營收 Revenue | C2: 銷貨成本 COGS | D2: 人事費用 Payroll | E2: 租金 Rent | F2: 行銷費用 Marketing | G2: 其他費用 Other | H2: 毛利 Gross Profit | I2: 毛利率 Gross Margin | J2: 營業費用合計 Total OpEx | K2: 營業利益 Operating Income | L2: 營業利益率 OI Margin | M2: 備註 Notes
A3: 46054 | H3: =B3-C3 | I3: =IF(B3=0,"",H3/B3) | J3: =D3+E3+F3+G3 | K3: =H3-J3 | L3: =IF(B3=0,"",K3/B3)
A4: 46055 | H4: =B4-C4 | I4: =IF(B4=0,"",H4/B4) | J4: =D4+E4+F4+G4 | K4: =H4-J4 | L4: =IF(B4=0,"",K4/B4)
A5: 46056 | H5: =B5-C5 | I5: =IF(B5=0,"",H5/B5) | J5: =D5+E5+F5+G5 | K5: =H5-J5 | L5: =IF(B5=0,"",K5/B5)
A6: 46057 | H6: =B6-C6 | I6: =IF(B6=0,"",H6/B6) | J6: =D6+E6+F6+G6 | K6: =H6-J6 | L6: =IF(B6=0,"",K6/B6)
A7: 46058 | H7: =B7-C7 | I7: =IF(B7=0,"",H7/B7) | J7: =D7+E7+F7+G7 | K7: =H7-J7 | L7: =IF(B7=0,"",K7/B7)
A8: 46059 | H8: =B8-C8 | I8: =IF(B8=0,"",H8/B8) | J8: =D8+E8+F8+G8 | K8: =H8-J8 | L8: =IF(B8=0,"",K8/B8)
A9: 46060 | H9: =B9-C9 | I9: =IF(B9=0,"",H9/B9) | J9: =D9+E9+F9+G9 | K9: =H9-J9 | L9: =IF(B9=0,"",K9/B9)
A10: 46061 | H10: =B10-C10 | I10: =IF(B10=0,"",H10/B10) | J10: =D10+E10+F10+G10 | K10: =H10-J10 | L10: =IF(B10=0,"",K10/B10)
A11: 46062 | H11: =B11-C11 | I11: =IF(B11=0,"",H11/B11) | J11: =D11+E11+F11+G11 | K11: =H11-J11 | L11: =IF(B11=0,"",K11/B11)
A12: 46063 | H12: =B12-C12 | I12: =IF(B12=0,"",H12/B12) | J12: =D12+E12+F12+G12 | K12: =H12-J12 | L12: =IF(B12=0,"",K12/B12)
A13: 46064 | H13: =B13-C13 | I13: =IF(B13=0,"",H13/B13) | J13: =D13+E13+F13+G13 | K13: =H13-J13 | L13: =IF(B13=0,"",K13/B13)
A14: 46065 | H14: =B14-C14 | I14: =IF(B14=0,"",H14/B14) | J14: =D14+E14+F14+G14 | K14: =H14-J14 | L14: =IF(B14=0,"",K14/B14)
... A30: 46081 | H30: =B30-C30 | I30: =IF(B30=0,"",H30/B30) | J30: =D30+E30+F30+G30 | K30: =H30-J30 | L30: =IF(B30=0,"",K30/B30)
A31: 合計 Total | B31: =SUM(B3:B32) | C31: =SUM(C3:C32) | D31: =SUM(D3:D32) | E31: =SUM(E3:E32) | F31: =SUM(F3:F32) | G31: =SUM(G3:G32) | H31: =SUM(H3:H32) | I31: =IF(B33=0,"",H33/B33) | J31: =SUM(J3:J32) | K31: =SUM(K3:K32) | L31: =IF(B33=0,"",K33/B33)

Sheet 月報表 Monthly Summary
A1: 月度財務摘要 Monthly Financial Summary
A2: 月份 Month | B2: 總營收 Revenue | C2: 總成本 COGS | D2: 毛利 Gross Profit | E2: 毛利率 Gross Margin | F2: 總費用 Total OpEx | G2: 營業利益 Op. Income | H2: 營業利益率 OI Margin
A3: 1月 | B3: =SUMPRODUCT((MONTH('每日記錄 Daily Input'!A3:A32)=1)*'每日記錄 Daily Input'!B3:B32) | C3: =SUMPRODUCT((MONTH('每日記錄 Daily Input'!A3:A32)=1)*'每日記錄 Daily Input'!C3:C32) | D3: =B3-C3 | E3: =IF(B3=0,"",D3/B3) | F3: =SUMPRODUCT((MONTH('每日記錄 Daily Input'!A3:A32)=1)*'每日記錄 Daily Input'!J3:J32) | G3: =D3-F3 | H3: =IF(B3=0,"",G3/B3)
A4: 2月 | B4: =SUMPRODUCT((MONTH('每日記錄 Daily Input'!A3:A32)=2)*'每日記錄 Daily Input'!B3:B32) | C4: =SUMPRODUCT((MONTH('每日記錄 Daily Input'!A3:A32)=2)*'每日記錄 Daily Input'!C3:C32) | D4: =B4-C4 | E4: =IF(B4=0,"",D4/B4) | F4: =SUMPRODUCT((MONTH('每日記錄 Daily Input'!A3:A32)=2)*'每日記錄 Daily Input'!J3:J32) | G4: =D4-F4 | H4: =IF(B4=0,"",G4/B4)
A5: 3月 | B5: =SUMPRODUCT((MONTH('每日記錄 Daily Input'!A3:A32)=3)*'每日記錄 Daily Input'!B3:B32) | C5: =SUMPRODUCT((MONTH('每日記錄 Daily Input'!A3:A32)=3)*'每日記錄 Daily Input'!C3:C32) | D5: =B5-C5 | E5: =IF(B5=0,"",D5/B5) | F5: =SUMPRODUCT((MONTH('每日記錄 Daily Input'!A3:A32)=3)*'每日記錄 Daily Input'!J3:J32) | G5: =D5-F5 | H5: =IF(B5=0,"",G5/B5)
A6: 4月 | B6: =SUMPRODUCT((MONTH('每日記錄 Daily Input'!A3:A32)=4)*'每日記錄 Daily Input'!B3:B32) | C6: =SUMPRODUCT((MONTH('每日記錄 Daily Input'!A3:A32)=4)*'每日記錄 Daily Input'!C3:C32) | D6: =B6-C6 | E6: =IF(B6=0,"",D6/B6) | F6: =SUMPRODUCT((MONTH('每日記錄 Daily Input'!A3:A32)=4)*'每日記錄 Daily Input'!J3:J32) | G6: =D6-F6 | H6: =IF(B6=0,"",G6/B6)
A7: 5月 | B7: =SUMPRODUCT((MONTH('每日記錄 Daily Input'!A3:A32)=5)*'每日記錄 Daily Input'!B3:B32) | C7: =SUMPRODUCT((MONTH('每日記錄 Daily Input'!A3:A32)=5)*'每日記錄 Daily Input'!C3:C32) | D7: =B7-C7 | E7: =IF(B7=0,"",D7/B7) | F7: =SUMPRODUCT((MONTH('每日記錄 Daily Input'!A3:A32)=5)*'每日記錄 Daily Input'!J3:J32) | G7: =D7-F7 | H7: =IF(B7=0,"",G7/B7)
A8: 6月 | B8: =SUMPRODUCT((MONTH('每日記錄 Daily Input'!A3:A32)=6)*'每日記錄 Daily Input'!B3:B32) | C8: =SUMPRODUCT((MONTH('每日記錄 Daily Input'!A3:A32)=6)*'每日記錄 Daily Input'!C3:C32) | D8: =B8-C8 | E8: =IF(B8=0,"",D8/B8) | F8: =SUMPRODUCT((MONTH('每日記錄 Daily Input'!A3:A32)=6)*'每日記錄 Daily Input'!J3:J32) | G8: =D8-F8 | H8: =IF(B8=0,"",G8/B8)
A9: 7月 | B9: =SUMPRODUCT((MONTH('每日記錄 Daily Input'!A3:A32)=7)*'每日記錄 Daily Input'!B3:B32) | C9: =SUMPRODUCT((MONTH('每日記錄 Daily Input'!A3:A32)=7)*'每日記錄 Daily Input'!C3:C32) | D9: =B9-C9 | E9: =IF(B9=0,"",D9/B9) | F9: =SUMPRODUCT((MONTH('每日記錄 Daily Input'!A3:A32)=7)*'每日記錄 Daily Input'!J3:J32) | G9: =D9-F9 | H9: =IF(B9=0,"",G9/B9)
A10: 8月 | B10: =SUMPRODUCT((MONTH('每日記錄 Daily Input'!A3:A32)=8)*'每日記錄 Daily Input'!B3:B32) | C10: =SUMPRODUCT((MONTH('每日記錄 Daily Input'!A3:A32)=8)*'每日記錄 Daily Input'!C3:C32) | D10: =B10-C10 | E10: =IF(B10=0,"",D10/B10) | F10: =SUMPRODUCT((MONTH('每日記錄 Daily Input'!A3:A32)=8)*'每日記錄 Daily Input'!J3:J32) | G10: =D10-F10 | H10: =IF(B10=0,"",G10/B10)
A11: 9月 | B11: =SUMPRODUCT((MONTH('每日記錄 Daily Input'!A3:A32)=9)*'每日記錄 Daily Input'!B3:B32) | C11: =SUMPRODUCT((MONTH('每日記錄 Daily Input'!A3:A32)=9)*'每日記錄 Daily Input'!C3:C32) | D11: =B11-C11 | E11: =IF(B11=0,"",D11/B11) | F11: =SUMPRODUCT((MONTH('每日記錄 Daily Input'!A3:A32)=9)*'每日記錄 Daily Input'!J3:J32) | G11: =D11-F11 | H11: =IF(B11=0,"",G11/B11)
A12: 10月 | B12: =SUMPRODUCT((MONTH('每日記錄 Daily Input'!A3:A32)=10)*'每日記錄 Daily Input'!B3:B32) | C12: =SUMPRODUCT((MONTH('每日記錄 Daily Input'!A3:A32)=10)*'每日記錄 Daily Input'!C3:C32) | D12: =B12-C12 | E12: =IF(B12=0,"",D12/B12) | F12: =SUMPRODUCT((MONTH('每日記錄 Daily Input'!A3:A32)=10)*'每日記錄 Daily Input'!J3:J32) | G12: =D12-F12 | H12: =IF(B12=0,"",G12/B12)
A13: 11月 | B13: =SUMPRODUCT((MONTH('每日記錄 Daily Input'!A3:A32)=11)*'每日記錄 Daily Input'!B3:B32) | C13: =SUMPRODUCT((MONTH('每日記錄 Daily Input'!A3:A32)=11)*'每日記錄 Daily Input'!C3:C32) | D13: =B13-C13 | E13: =IF(B13=0,"",D13/B13) | F13: =SUMPRODUCT((MONTH('每日記錄 Daily Input'!A3:A32)=11)*'每日記錄 Daily Input'!J3:J32) | G13: =D13-F13 | H13: =IF(B13=0,"",G13/B13)
A14: 12月 | B14: =SUMPRODUCT((MONTH('每日記錄 Daily Input'!A3:A32)=12)*'每日記錄 Daily Input'!B3:B32) | C14: =SUMPRODUCT((MONTH('每日記錄 Daily Input'!A3:A32)=12)*'每日記錄 Daily Input'!C3:C32) | D14: =B14-C14 | E14: =IF(B14=0,"",D14/B14) | F14: =SUMPRODUCT((MONTH('每日記錄 Daily Input'!A3:A32)=12)*'每日記錄 Daily Input'!J3:J32) | G14: =D14-F14 | H14: =IF(B14=0,"",G14/B14)
A15: 年度合計 Annual | B15: =SUM(B3:B14) | C15: =SUM(C3:C14) | D15: =SUM(D3:D14) | E15: =IF(B15=0,"",D15/B15) | F15: =SUM(F3:F14) | G15: =SUM(G3:G14) | H15: =IF(B15=0,"",G15/B15)

Sheet 儀表板 Dashboard
A1: 財務儀表板 Financial Dashboard
B3: 本月營收 Revenue | E3: 毛利率 Gross Margin | H3: 營業利益 Op. Income
B4: ='月報表 Monthly Summary'!B4 | E4: ='月報表 Monthly Summary'!E4 | H4: ='月報表 Monthly Summary'!G4
A25: 人事費用 Payroll | B25: =SUMPRODUCT((MONTH('每日記錄 Daily Input'!A3:A32)=MONTH(TODAY()))*'每日記錄 Daily Input'!D3:D32)
A26: 租金 Rent | B26: =SUMPRODUCT((MONTH('每日記錄 Daily Input'!A3:A32)=MONTH(TODAY()))*'每日記錄 Daily Input'!E3:E32)
A27: 行銷費用 Marketing | B27: =SUMPRODUCT((MONTH('每日記錄 Daily Input'!A3:A32)=MONTH(TODAY()))*'每日記錄 Daily Input'!F3:F32)
A28: 其他費用 Other | B28: =SUMPRODUCT((MONTH('每日記錄 Daily Input'!A3:A32)=MONTH(TODAY()))*'每日記錄 Daily Input'!G3:G32)
